{
  "package.json": {
    "name": "package.json",
    "type": "file",
    "path": "utils/models/basic/package.json",
    "replace": { "$name": "$name" }
  },
  "install": {
    "name": "npm i",
    "type": "command"
  },
  "config.js": {
    "name": "config.js",
    "type": "file",
    "path": "utils/models/basic/config.js"
  },
  "app.js": {
    "name": "app.js",
    "type": "file",
    "path": "utils/models/basic/app.js"
  },
  "Dockerfile": {
    "name": "Dockerfile",
    "type": "file",
    "path": "utils/models/basic/Dockerfile"
  },
  ".env.example": {
    "name": ".env.example",
    "type": "file",
    "path": "utils/models/basic/.env.example"
  },
  ".prettierrc.json": {
    "name": ".prettierrc.json",
    "type": "file",
    "path": "utils/models/basic/.prettierrc.json"
  },
  "vendor": {
    "name": "vendor",
    "type": "directory",
    "childrens": {
      "http": {
        "name": "http",
        "type": "directory",
        "childrens": {
          "controllers": {
            "name": "controllers",
            "type": "directory",
            "childrens": {
              "Controller.js": {
                "name": "Controller.js",
                "type": "file",
                "path": "utils/models/controllers/Controller.js"
              }
            }
          },
          "requests": {
            "name": "requests",
            "type": "directory",
            "childrens": {
              "Request.js": {
                "name": "Request.js",
                "type": "file",
                "path": "utils/models/requests/Request.js"
              }
            }
          }
        }
      },
      "db": {
        "name": "db",
        "type": "directory",
        "childrens": {
          "BaseModel.js": {
            "name": "BaseModel.js",
            "type": "file",
            "path": "utils/models/database/BaseModel.js"
          }
        }
      }
    }
  },
  "controllers": {
    "name": "controllers",
    "type": "directory",
    "childrens": {
      "HomeController.js": {
        "name": "HomeController.js",
        "type": "file",
        "path": "utils/models/controllers/BaseController.js",
        "replace": { "$name": "HomeController" }
      }
    }
  },
  "database": {
    "name": "database",
    "type": "directory",
    "childrens": {
      "migrations": {
        "name": "migrations",
        "type": "directory",
        "childrens": {}
      },
      "models": {
        "name": "models",
        "type": "directory",
        "childrens": {
          "UserModel.js": {
            "name": "UserModel.js",
            "type": "file",
            "path": "utils/models/database/UserModel.js"
          }
        }
      },
      "seeders": {
        "name": "seeders",
        "type": "directory",
        "childrens": {}
      }
    }
  },
  "resources": {
    "name": "resources",
    "type": "directory",
    "childrens": {
      "views": {
        "name": "views",
        "type": "directory",
        "childrens": {
          "base.jinja": {
            "name": "base.jinja",
            "type": "file",
            "path": "utils/models/views/base.jinja",
            "replace": { "$name": "$name" }
          }
        }
      },
      "images": {
        "name": "images",
        "type": "directory",
        "childrens": {}
      },
      "static": {
        "name": "static",
        "type": "directory",
        "childrens": {
          "images": {
            "name": "images",
            "type": "directory",
            "childrens": {}
          },
          "styles": {
            "name": "styles",
            "type": "directory",
            "childrens": {
              "style.sass": {
                "name": "style.sass",
                "type": "file",
                "path": "utils/models/styles/style.sass"
              }
            }
          },
          "javascripts": {
            "name": "javascripts",
            "type": "directory",
            "childrens": {
              "index.js": {
                "name": "index.js",
                "type": "file",
                "path": "utils/models/javascripts/index.js"
              }
            }
          }
        }
      }
    }
  }
}
